airavata_jupyter_magic.py
device_auth.py
airavata_jupyter_magic-1.0.5.dist-info/METADATA
airavata_jupyter_magic-1.0.5.dist-info/WHEEL
airavata_jupyter_magic-1.0.5.dist-info/top_level.txt
airavata_jupyter_magic-1.0.5.dist-info/RECORD
