Metadata-Version: 2.2
Name: airavata-jupyter-magic
Version: 1.0.5
Summary: Jupyter magics for running notebook cells on remote HPC resources. Powered by Apache Airavata.
Author-email: Yasith Jayawardana <yasith@gatech.edu>, Dimuthu Wannipurage <dimuthuw@gatech.edu>, Lahiru Jayathilake <ljayathilake3@gatech.edu>
License: Apache-2.0
Project-URL: Homepage, https://github.com/apache/airavata
Project-URL: Repository, https://github.com/apache/airavata
Requires-Dist: requests
Requires-Dist: PyJWT
Requires-Dist: ipython
Provides-Extra: dev
Requires-Dist: black; extra == "dev"
Requires-Dist: flake8; extra == "dev"
